yaml_helper/__init__.py
yaml_helper/yaml_helper.py
yaml_helper-0.1.0.dist-info/LICENSE
yaml_helper-0.1.0.dist-info/METADATA
yaml_helper-0.1.0.dist-info/WHEEL
yaml_helper-0.1.0.dist-info/top_level.txt
yaml_helper-0.1.0.dist-info/RECORD
